{
  "source": "fresh_stage42_gx_ucy_h100_candidate_integrity_manifest",
  "stage": "Stage42-GX UCY h100 candidate integrity manifest",
  "generated_at_utc": "2026-05-27T15:08:36.390226+00:00",
  "git_commit": "0eafd4b",
  "input_hash": "e4c20dd9b287703803211db5681b7dc8506b4fa15fdf4b567cd0c905283e3eec",
  "current_facts": [
    "当前不是 true 3D world model。",
    "当前不是 large-scale foundation world model。",
    "当前仍是 protected dataset-local / raw-frame 2.5D 多智能体 world-state candidate。",
    "Stage42-GX 只生成 UCY h100 candidate integrity manifest，不下载、不转换、不训练、不评估。",
    "文件 hash、路径存在和 parseability 不等于 legal permission 或 conversion readiness。",
    "terms accepted、local path、source identity、guarded conversion、no-leakage/source-CV 都通过前，不能把 repair 写成完成。",
    "future endpoints / waypoints 只允许作为 supervised/evaluation labels，不能作为 inference input。",
    "不使用 central velocity，不使用 test endpoints 构建 goals，不使用 test metrics 调 threshold。",
    "t+50 / t+100 仍是 raw-frame horizon，不能写成 seconds-level。",
    "dataset-local/raw-frame 不能写成 global metric。",
    "Stage5C latent generative 未执行。",
    "SMC 未启用。"
  ],
  "summary": {
    "source": "fresh_stage42_gx_ucy_h100_candidate_integrity_manifest",
    "input_gw_verdict": "stage42_gw_h100_blocker_closure_decision_pass",
    "input_fq_verdict": "stage42_fq_h100_source_support_repair_queue_pass",
    "input_fs_verdict": "stage42_fs_ucy_h100_terms_intake_validator_pass",
    "candidate_rows": 6,
    "existing_files": 6,
    "target_family_candidates": 2,
    "t100_capable_files": 6,
    "total_parsed_rows": 98032,
    "total_parsed_t100_windows": 11848,
    "unique_hashes": 6,
    "conversion_ready_now_count": 0,
    "downloaded_now": 0,
    "converted_now": 0,
    "evaluated_now": 0,
    "ucy_gw_closure_status": "blocked_by_terms_and_conversion_readiness",
    "ucy_gw_legal_conversion_ready": false,
    "uniform_h100_or_t100_claim_allowed": false,
    "stage5c_executed": false,
    "smc_enabled": false
  },
  "candidate_integrity_rows": [
    {
      "relative_path": "UCY/zara02/obsmat.txt",
      "absolute_path": "external_data/OpenTraj/datasets/UCY/zara02/obsmat.txt",
      "source_identity_suggestion": "UCY::zara02::obsmat",
      "exists": true,
      "sha256": "0b29bdacd54b971299b741f291d9b0eac0ce9aeec9901e75576c529a39523e9b",
      "file_size_bytes": 1208066,
      "family_bucket": "zara",
      "target_bucket_match": true,
      "priority_score": 40,
      "candidate_estimated_t100_windows": 2095,
      "parsed_rows": 9537,
      "skipped_rows": 0,
      "unique_agents": 204,
      "unique_frames": 1052,
      "min_frame": 7,
      "max_frame": 10517,
      "common_frame_step": 10,
      "max_track_points": 583,
      "t100_capable": true,
      "parsed_estimated_t100_windows": 2095,
      "loader_supported": true,
      "synthetic_or_diagnostic": false,
      "raw_content_stored_in_manifest": false,
      "conversion_ready_now": false,
      "conversion_executed": false,
      "evaluation_executed": false,
      "legal_status": "terms_unverified_user_confirmation_required"
    },
    {
      "relative_path": "UCY/zara01/obsmat.txt",
      "absolute_path": "external_data/OpenTraj/datasets/UCY/zara01/obsmat.txt",
      "source_identity_suggestion": "UCY::zara01::obsmat",
      "exists": true,
      "sha256": "bd999ebcfbc506821fa5032a10b9101e150defcff85f1ef037d09ce7c6a8c2aa",
      "file_size_bytes": 632141,
      "family_bucket": "zara",
      "target_bucket_match": true,
      "priority_score": 23,
      "candidate_estimated_t100_windows": 97,
      "parsed_rows": 5024,
      "skipped_rows": 0,
      "unique_agents": 148,
      "unique_frames": 866,
      "min_frame": 1,
      "max_frame": 9011,
      "common_frame_step": 10,
      "max_track_points": 197,
      "t100_capable": true,
      "parsed_estimated_t100_windows": 97,
      "loader_supported": true,
      "synthetic_or_diagnostic": false,
      "raw_content_stored_in_manifest": false,
      "conversion_ready_now": false,
      "conversion_executed": false,
      "evaluation_executed": false,
      "legal_status": "terms_unverified_user_confirmation_required"
    },
    {
      "relative_path": "UCY/students01/students001.txt",
      "absolute_path": "external_data/OpenTraj/datasets/UCY/students01/students001.txt",
      "source_identity_suggestion": "UCY::students01::students001",
      "exists": true,
      "sha256": "a6d87f278d94136fe39b8be91555487a29ac77259ae403b9dba2d5c18caf7b5b",
      "file_size_bytes": 879714,
      "family_bucket": "students",
      "target_bucket_match": false,
      "priority_score": 25,
      "candidate_estimated_t100_windows": 1949,
      "parsed_rows": 21813,
      "skipped_rows": 0,
      "unique_agents": 415,
      "unique_frames": 444,
      "min_frame": 0,
      "max_frame": 4430,
      "common_frame_step": 10,
      "max_track_points": 352,
      "t100_capable": true,
      "parsed_estimated_t100_windows": 1949,
      "loader_supported": true,
      "synthetic_or_diagnostic": false,
      "raw_content_stored_in_manifest": false,
      "conversion_ready_now": false,
      "conversion_executed": false,
      "evaluation_executed": false,
      "legal_status": "terms_unverified_user_confirmation_required"
    },
    {
      "relative_path": "UCY/students03/obsmat.txt",
      "absolute_path": "external_data/OpenTraj/datasets/UCY/students03/obsmat.txt",
      "source_identity_suggestion": "UCY::students03::obsmat",
      "exists": true,
      "sha256": "d9fd7048eab7d3d9550d7ac4f59b19d97a87612310e8c8e48cf3aaf59764ff80",
      "file_size_bytes": 2752596,
      "family_bucket": "students",
      "target_bucket_match": false,
      "priority_score": 25,
      "candidate_estimated_t100_windows": 3413,
      "parsed_rows": 21846,
      "skipped_rows": 0,
      "unique_agents": 428,
      "unique_frames": 540,
      "min_frame": 1,
      "max_frame": 5391,
      "common_frame_step": 10,
      "max_track_points": 539,
      "t100_capable": true,
      "parsed_estimated_t100_windows": 3413,
      "loader_supported": true,
      "synthetic_or_diagnostic": false,
      "raw_content_stored_in_manifest": false,
      "conversion_ready_now": false,
      "conversion_executed": false,
      "evaluation_executed": false,
      "legal_status": "terms_unverified_user_confirmation_required"
    },
    {
      "relative_path": "UCY/students03/obsmat_px.txt",
      "absolute_path": "external_data/OpenTraj/datasets/UCY/students03/obsmat_px.txt",
      "source_identity_suggestion": "UCY::students03::obsmat_px",
      "exists": true,
      "sha256": "8286c024198b78904938412f69a11dd61940a5eafdf4bcd4ab791ab084007fdb",
      "file_size_bytes": 2819811,
      "family_bucket": "students",
      "target_bucket_match": false,
      "priority_score": 25,
      "candidate_estimated_t100_windows": 3415,
      "parsed_rows": 21859,
      "skipped_rows": 0,
      "unique_agents": 428,
      "unique_frames": 540,
      "min_frame": 1,
      "max_frame": 5391,
      "common_frame_step": 10,
      "max_track_points": 540,
      "t100_capable": true,
      "parsed_estimated_t100_windows": 3415,
      "loader_supported": true,
      "synthetic_or_diagnostic": false,
      "raw_content_stored_in_manifest": false,
      "conversion_ready_now": false,
      "conversion_executed": false,
      "evaluation_executed": false,
      "legal_status": "terms_unverified_user_confirmation_required"
    },
    {
      "relative_path": "UCY/students03/students003.txt",
      "absolute_path": "external_data/OpenTraj/datasets/UCY/students03/students003.txt",
      "source_identity_suggestion": "UCY::students03::students003",
      "exists": true,
      "sha256": "e25798b660634330aa89f8bb259425de720e84d0873902726c1d1f4ccff21d6c",
      "file_size_bytes": 724279,
      "family_bucket": "students",
      "target_bucket_match": false,
      "priority_score": 15,
      "candidate_estimated_t100_windows": 879,
      "parsed_rows": 17953,
      "skipped_rows": 0,
      "unique_agents": 434,
      "unique_frames": 541,
      "min_frame": 0,
      "max_frame": 5400,
      "common_frame_step": 10,
      "max_track_points": 289,
      "t100_capable": true,
      "parsed_estimated_t100_windows": 879,
      "loader_supported": true,
      "synthetic_or_diagnostic": false,
      "raw_content_stored_in_manifest": false,
      "conversion_ready_now": false,
      "conversion_executed": false,
      "evaluation_executed": false,
      "legal_status": "terms_unverified_user_confirmation_required"
    }
  ],
  "user_action_required": [
    {
      "priority": "critical",
      "relative_path": "UCY/zara02/obsmat.txt",
      "source_identity_suggestion": "UCY::zara02::obsmat",
      "sha256": "0b29bdacd54b971299b741f291d9b0eac0ce9aeec9901e75576c529a39523e9b",
      "action": "If the user has accepted UCY official terms, copy the source_identity_suggestion into the terms intake and confirm allowed use/local path. Do not run conversion before validator readiness.",
      "claim_guard": "Hash/path integrity is not permission, conversion, evaluation, metric evidence, or h100 repair."
    },
    {
      "priority": "critical",
      "relative_path": "UCY/zara01/obsmat.txt",
      "source_identity_suggestion": "UCY::zara01::obsmat",
      "sha256": "bd999ebcfbc506821fa5032a10b9101e150defcff85f1ef037d09ce7c6a8c2aa",
      "action": "If the user has accepted UCY official terms, copy the source_identity_suggestion into the terms intake and confirm allowed use/local path. Do not run conversion before validator readiness.",
      "claim_guard": "Hash/path integrity is not permission, conversion, evaluation, metric evidence, or h100 repair."
    },
    {
      "priority": "supporting",
      "relative_path": "UCY/students01/students001.txt",
      "source_identity_suggestion": "UCY::students01::students001",
      "sha256": "a6d87f278d94136fe39b8be91555487a29ac77259ae403b9dba2d5c18caf7b5b",
      "action": "If the user has accepted UCY official terms, copy the source_identity_suggestion into the terms intake and confirm allowed use/local path. Do not run conversion before validator readiness.",
      "claim_guard": "Hash/path integrity is not permission, conversion, evaluation, metric evidence, or h100 repair."
    },
    {
      "priority": "supporting",
      "relative_path": "UCY/students03/obsmat.txt",
      "source_identity_suggestion": "UCY::students03::obsmat",
      "sha256": "d9fd7048eab7d3d9550d7ac4f59b19d97a87612310e8c8e48cf3aaf59764ff80",
      "action": "If the user has accepted UCY official terms, copy the source_identity_suggestion into the terms intake and confirm allowed use/local path. Do not run conversion before validator readiness.",
      "claim_guard": "Hash/path integrity is not permission, conversion, evaluation, metric evidence, or h100 repair."
    },
    {
      "priority": "supporting",
      "relative_path": "UCY/students03/obsmat_px.txt",
      "source_identity_suggestion": "UCY::students03::obsmat_px",
      "sha256": "8286c024198b78904938412f69a11dd61940a5eafdf4bcd4ab791ab084007fdb",
      "action": "If the user has accepted UCY official terms, copy the source_identity_suggestion into the terms intake and confirm allowed use/local path. Do not run conversion before validator readiness.",
      "claim_guard": "Hash/path integrity is not permission, conversion, evaluation, metric evidence, or h100 repair."
    },
    {
      "priority": "supporting",
      "relative_path": "UCY/students03/students003.txt",
      "source_identity_suggestion": "UCY::students03::students003",
      "sha256": "e25798b660634330aa89f8bb259425de720e84d0873902726c1d1f4ccff21d6c",
      "action": "If the user has accepted UCY official terms, copy the source_identity_suggestion into the terms intake and confirm allowed use/local path. Do not run conversion before validator readiness.",
      "claim_guard": "Hash/path integrity is not permission, conversion, evaluation, metric evidence, or h100 repair."
    }
  ],
  "user_action_required_written": true,
  "no_leakage": {
    "future_endpoint_input": false,
    "future_waypoint_input": false,
    "central_velocity": false,
    "test_endpoint_goals": false,
    "test_threshold_tuning": false,
    "manifest_only_no_conversion": true
  },
  "claim_boundary": {
    "true_3d": false,
    "foundation_world_model": false,
    "global_metric_claim_allowed": false,
    "global_seconds_claim_allowed": false,
    "uniform_h100_or_t100_claim_allowed": false,
    "raw_data_committed": false,
    "download_executed": false,
    "conversion_executed": false,
    "training_executed": false,
    "evaluation_executed": false,
    "stage5c_executed": false,
    "smc_enabled": false
  },
  "stage42_gx_gate": {
    "source": "fresh_stage42_gx_ucy_h100_candidate_integrity_manifest",
    "gates": {
      "gw_input_verified": true,
      "fq_input_verified": true,
      "fs_input_verified": true,
      "ucy_candidates_loaded": true,
      "all_candidate_files_exist": true,
      "target_family_candidates_present": true,
      "hashes_computed": true,
      "parsed_stats_computed": true,
      "raw_content_not_stored": true,
      "legal_blocker_preserved": true,
      "no_conversion_ready_claim": true,
      "no_download_conversion_eval": true,
      "user_action_written": true,
      "no_future_test_or_central_velocity_leakage": true,
      "no_metric_seconds_overclaim": true,
      "stage5c_false": true,
      "smc_false": true
    },
    "passed": 17,
    "total": 17,
    "verdict": "stage42_gx_ucy_h100_candidate_integrity_manifest_pass"
  }
}